clibbeam/Makefile
clibbeam/array.c
clibbeam/beam.c
clibbeam/beam.h
pyant/__init__.py
pyant/beam.py
pyant/clib.py
pyant/fitting.py
pyant/plotting.py
pyant/py.typed
pyant/statistics.py
pyant/types.py
pyant/utils.py
pyant/version.py
pyant/beams/__init__.py
pyant/beams/arrays.py
pyant/models/__init__.py
pyant/models/airy.py
pyant/models/array.py
pyant/models/cassegrain.py
pyant/models/finite_cylindrical_parabola.py
pyant/models/gaussian.py
pyant/models/harmonic_series.py
pyant/models/interpolated.py
pyant/models/interpolated_array.py
pyant/models/isotropic.py
pyant/models/measured.py
pyant/models/phased_finite_cylindrical_parabola.py
pyant/models/polynomial.py
pyant-1.1.0.dist-info/licenses/LICENSE
pyant-1.1.0.dist-info/METADATA
pyant-1.1.0.dist-info/WHEEL
pyant-1.1.0.dist-info/top_level.txt
pyant-1.1.0.dist-info/RECORD
