Metadata-Version: 2.4
Name: pyant
Version: 1.1.0
Summary: Radar antenna models in python
Author-email: Daniel Kastinen <daniel.kastinen@irf.se>, Tom Grydeland <tgry@norceresearch.no>, Juha Vierinen <juha-pekka.vierinen@uit.no>
Maintainer-email: Daniel Kastinen <daniel.kastinen@irf.se>
License: MIT License
Project-URL: Documentation, https://danielk.developer.irf.se/pyant/
Project-URL: Repository, https://github.com/danielk333/pyant
Classifier: Intended Audience :: Science/Research
Classifier: Programming Language :: Python :: 3
Classifier: Topic :: Scientific/Engineering :: Physics
Classifier: Operating System :: OS Independent
Classifier: License :: OSI Approved :: MIT License
Requires-Python: >=3.10
License-File: LICENSE
Requires-Dist: numpy>=2
Requires-Dist: scipy>=1.10.0
Requires-Dist: spacecoords>=0.1.0
Provides-Extra: plotting
Requires-Dist: matplotlib>=3.2.0; extra == "plotting"
Provides-Extra: develop
Requires-Dist: pytest; extra == "develop"
Requires-Dist: flake8; extra == "develop"
Requires-Dist: wheel; extra == "develop"
Requires-Dist: build; extra == "develop"
Requires-Dist: twine; extra == "develop"
Requires-Dist: pytest-cov; extra == "develop"
Requires-Dist: matplotlib; extra == "develop"
Requires-Dist: ipykernel; extra == "develop"
Requires-Dist: radon; extra == "develop"
Requires-Dist: numpydoc; extra == "develop"
Requires-Dist: black; extra == "develop"
Requires-Dist: auditwheel; extra == "develop"
Requires-Dist: patchelf; extra == "develop"
Requires-Dist: mkdocs-material; extra == "develop"
Requires-Dist: mkdocstrings[python]; extra == "develop"
Requires-Dist: mkdocs-jupyter; extra == "develop"
Requires-Dist: mkdocs-gen-files; extra == "develop"
Requires-Dist: mkdocs-literate-nav; extra == "develop"
Requires-Dist: mkdocs-section-index; extra == "develop"
Provides-Extra: tests
Requires-Dist: pytest; extra == "tests"
Requires-Dist: pytest-cov; extra == "tests"
Dynamic: license-file
